[{"FullLog":"🧔🪓 sirlarson 24:36 ⚡🏆🧝🌿 luiza_lon | 🛡:💨 | 5:7 | 6:7 | 💨:6 | 6:🛡 | 💨:❌ | 4:💨 | 4:🛡 | 💨:🛡 | 4:4 | 7:0"},{"FullLog":"⚡🧔🦴 verdoga 22:29 🏆👹👁️ wild_blaze | 7:8 | 💨:10 | 5:💨 | 10:11"},{"FullLog":"⚡🏆🧔🪓 kekstant1n 27:13 💀✝️ skufenberg | ❌:4 | 8:💨 | 5:5 | 7:4 | 7:0"},{"FullLog":"🧝👁️ milyvolk 26:25 ⚡🏆🧑🌿 rabizza | 7:💨 | 💨:8 | 4:💨 | 4:7 | 5:11 | 5:0"},{"FullLog":"🏆🧔🪓 sirlarson 31:22 ⚡🧑🎸 neplana | 3:💥8 | 5:5 | 7:8 | 7:💥10"},{"FullLog":"⚡🧝🪓 runolfr 17:33 🏆👹✨ cinetra_ | 6:7 | 6:7 | ❌:9 | 5:10"},{"FullLog":"👹🪓 jed1master 27:34 ⚡🏆🧝⚔️ workers12 | 🛡:5 | 6:💨 | 🛡:💨 | 💨:💨 | 7:💨 | 6:6 | 🛡:💥11 | 6:💨 | 🛡:5 | 5:🛡 | 4:0"},{"FullLog":"⚡🧔🪓 sirlarson 24:40 🏆💀✝️ t1ssar | 💨:💥9 | 5:4 | 7:8 | 💨:🛡 | 💨:5 | 8:🛡 | 4:💥14"},{"FullLog":"⚡👹⚙️ shenok07 26:29 🏆🧔🪓 kekstant1n | 🛡:4 | 💨:5 | 3:8 | 3:🛡 | 3:❌ | 10:4 | 7:💨 | 🛡:8"},{"FullLog":"🏆🧔🦴 verdoga 24:22 ⚡🧝🔮 filay_ww | 12:7 | 10:💥17"}]