[{"FullLog":"⚡🏆💀🗡️ elnino7727 28:8 🧝⚙️ velitar_game | 10:8 | 💥8:💨 | 10:0"},{"FullLog":"⚡🏆👹🥋 sirlarson 21:20 🧝🔮 catrosan | 5:4 | 5:7 | 6:9 | 5:0"},{"FullLog":"⚡🏆💀🎸 berlina4ka 33:19 👹🎸 ruby_lxz | 10:9 | 💨:6 | 8:4 | 💥15:0"},{"FullLog":"🏆🧝⚙️ velitar_game 27:14 ⚡🧑🏹 mixabot | 💨:5 | 3:💨 | 💨:5 | 4:8 | 7:9"},{"FullLog":"👹🥋 sirlarson 15:24 ⚡🏆💀✝️ t1ssar | 8:💨 | 🛡:8 | 9:7 | 7:0"},{"FullLog":"💀🗡️ elnino7727 18:22 ⚡🏆👹⚙️ shenok07 | 3:5 | 7:8 | 4:5 | 8:0"},{"FullLog":"⚡🧑🪓 aimion 22:37 🏆🧑🛡️ gotfat | 6:3 | 🛡:🛡 | 💨:2 | 5:3 | 🛡:5 | 4:7 | 💨:🛡 | 3:6 | 4:💨 | 💨:4 | ❌:7"},{"FullLog":"⚡👹🗡️ ded_evgenius 27:23 🏆🧑🌿 rabizza | 4:6 | 8:3 | 3:5 | 4:4 | 8:5"},{"FullLog":"⚡🏆💀🎸 rattge 30:18 👹✝️ ami_kron | ❌:6 | 5:6 | 9:6 | 💥16:0"},{"FullLog":"🏆💀🎸 berlina4ka 42:21 ⚡🧝🏹 equa4ka | ❌:5 | 8:8 | 5:10 | 8:💥19"}]