[{"FullLog":"⚡🏆👹🗡️ ded_evgenius 26:7 🧑🎸 ochirovatelnyi | 10:💨 | 8:7 | ❌:💨 | 8:0"},{"FullLog":"⚡🏆🧔🦴 kekstant1n 31:21 🧝⚔️ workers12 | 💨:8 | 8:5 | 💥10:4 | 7:4 | 6:0"},{"FullLog":"🧔🦴 verdoga 17:29 ⚡🏆🧑🗡️ realvoland | 7:💨 | 5:💥17 | 8:💨 | 9:0"},{"FullLog":"⚡🧝👁️ milyvolk 24:25 🏆🧔⚔️ aiko_wannaplay | 7:6 | 8:6 | 9:6 | 🛡:7"},{"FullLog":"🏆👹🪓 kotshiroyama 37:29 ⚡🧝🪓 araxizs | ❌:💨 | 💥12:🛡 | 6:7 | 🛡:💥9 | ❌:🛡 | 💨:4 | ❌:4 | 5:7 | 6:6"},{"FullLog":"🧔🦴 kekstant1n 12:25 ⚡🏆🧔🪓 taosblunt | 5:8 | 8:4 | 6:🛡 | 🛡:💨 | 6:0"},{"FullLog":"🧔🦴 verdoga 14:26 ⚡🏆💀🌿 bardeall | 7:8 | 6:6 | 6:💨 | 7:0"},{"FullLog":"💀🌿 bardeall 23:28 ⚡🏆👹⚔️ pavel_n1sm0 | 3:4 | 8:7 | 8:5 | 💨:7 | 9:0"},{"FullLog":"⚡🏆🧝👁️ milyvolk 29:17 🧑🌿 rabizza | 💨:💨 | 9:5 | ❌:6 | 9:6 | 11:0"},{"FullLog":"🧔🦴 k3nn3zy 17:33 ⚡🏆👹🗡️ ded_evgenius | 7:❌ | 6:9 | 10:8 | 10:0"}]