[{"FullLog":"🧝👁️ milyvolk 7:24 ⚡🏆💀🏹 rvotaenota | 11:7 | 4:❌ | 💨:💨 | 9:0"},{"FullLog":"⚡🏆💀🗡️ elnino7727 29:14 👹⚔️ pavel_n1sm0 | 9:💥9 | 4:💨 | 9:5 | 7:0"},{"FullLog":"⚡🏆🧑🛡️ retardedbird 31:13 💀🏹 rvotaenota | 8:3 | 6:💨 | 💥10:4 | ❌:6 | 7:0"},{"FullLog":"⚡💀🗡️ elnino7727 27:22 🏆🧑🛡️ retardedbird | 4:8 | 8:4 | 4:💨 | 4:5 | 7:5"},{"FullLog":"⚡🏆👹🗡️ ded_evgenius 34:9 💀🌿 bardeall | 9:9 | 9:❌ | 7:❌ | 9:0"},{"FullLog":"⚡🧔🦴 verdoga 9:27 🏆🧑🛡️ gotfat | 5:8 | 4:6 | 🛡:4 | 💨:5 | ❌:4"},{"FullLog":"⚡🏆👹🔮 velitar_game 34:17 🧔⚔️ aiko_wannaplay | 6:5 | 4:9 | 5:3 | 8:❌ | 11:0"},{"FullLog":"🧝👁️ milyvolk 10:24 ⚡🏆🧑🪓 aimion | 4:💨 | 8:10 | 💨:❌ | 4:🛡 | 4:💨 | 4:0"},{"FullLog":"🧝🌿 luiza_lon 22:29 ⚡🏆👹⚔️ pavel_n1sm0 | 💨:7 | 💥12:5 | 5:❌ | 3:6 | 4:4 | 5:0"},{"FullLog":"⚡🧔🪓 sirlarson 16:33 🏆🧑🏹 mixabot | 5:💥16 | 4:3 | 7:💥14"}]