[{"FullLog":"🧝🌿 luiza_lon 13:31 ⚡🏆🧝🏹 equa4ka | 9:5 | 4:4 | 💨:💨 | 8:4 | 4:💨 | 6:0"},{"FullLog":"⚡👹🗡️ ded_evgenius 13:22 🏆💀✝️ t1ssar | 7:💥18 | 6:4"},{"FullLog":"⚡🏆🧝👁️ milyvolk 22:11 🧝✨ insadge | 💨:❌ | 12:11 | 10:0"},{"FullLog":"💀🦴 new_wave_japanoise 10:29 ⚡🏆👹🦴 ibrooklyn_ | 5:❌ | 8:5 | 9:5 | 7:0"},{"FullLog":"🧑✨ bulbulatorz 4:26 ⚡🏆👹✝️ phili4pok | 💥13:💨 | 6:4 | 7:0"},{"FullLog":"⚡🏆🧝⚙️ velitar_game 24:12 💀🗡️ elnino7727 | 11:9 | 6:3 | 7:0"},{"FullLog":"🧝🔮 jed1master 13:20 ⚡🏆💀🗡️ elnino7727 | 5:8 | 5:5 | 10:0"},{"FullLog":"⚡👹⚙️ shenok07 21:24 🏆🧝🪓 runolfr | 3:5 | 💨:🛡 | 9:6 | 9:7 | ❌:6"},{"FullLog":"⚡👹🗡️ ded_evgenius 17:22 🏆🧝🔮 catrosan | 9:10 | 4:💨 | 4:12"},{"FullLog":"🧝🔮 jed1master 19:28 ⚡🏆👹🗡️ ded_evgenius | 7:11 | 💥12:8 | 9:0"}]