[{"FullLog":"⚡🧑🗡️ realvoland 9:29 🏆👹👁️ wild_blaze | 9:💥21 | ❌:8"},{"FullLog":"⚡🏆👹🗡️ ded_evgenius 30:7 🧝🌿 luiza_lon | 9:7 | 7:💨 | 5:❌ | 9:0"},{"FullLog":"⚡🏆💀🗡️ elnino7727 37:15 🧔🪓 sirlarson | 9:🛡 | 3:7 | 9:💨 | 8:8 | 8:0"},{"FullLog":"⚡🏆👹🪓 jed1master 38:21 🧝🪓 kot02 | 💨:❌ | 4:💨 | 🛡:5 | 🛡:🛡 | 💨:🛡 | 7:4 | ❌:💨 | 5:💨 | 6:6 | 🛡:🛡 | 5:6 | 5:🛡 | 6:0"},{"FullLog":"⚡🏆💀🎸 rattge 37:24 💀🪓 september4444 | 💨:🛡 | 💨:9 | 6:💨 | 6:9 | 💨:6 | 5:💨 | 10:💨 | 10:0"},{"FullLog":"⚡💀🏹 rvotaenota 20:33 🏆👹👁️ wild_blaze | 💨:6 | 💨:💨 | 9:11 | 11:💥16"},{"FullLog":"⚡🏆👹🗡️ ded_evgenius 23:16 💀🗡️ elnino7727 | 9:10 | 5:6 | 9:0"},{"FullLog":"🏆👹🪓 jed1master 28:32 ⚡💀🎸 rattge | 9:6 | 5:4 | 4:6 | 4:4 | 5:4 | 5:4"},{"FullLog":"⚡🏆👹👁️ wild_blaze 21:8 👹🗡️ ded_evgenius | 11:8 | 10:0"},{"FullLog":"👹🪓 jed1master 16:36 ⚡🏆👹👁️ wild_blaze | 9:7 | 9:4 | 10:5 | 8:0"}]